MANIFEST.in
setup.py
bin/upd89
etc/config.ini
init-script/upd89
upd89/__init__.py
upd89/agent.py
upd89/websrv.py
upd89.egg-info/PKG-INFO
upd89.egg-info/SOURCES.txt
upd89.egg-info/dependency_links.txt
upd89.egg-info/requires.txt
upd89.egg-info/top_level.txt
upd89/classes/__init__.py
upd89/classes/encoder.py
upd89/classes/package.py
upd89/classes/package_version.py
upd89/classes/packagelist.py
upd89/classes/repository.py
upd89/classes/system_notify.py
upd89/classes/system_register.py
upd89/classes/task_notify.py
upd89/classes/update.py
upd89/lib/__init__.py
upd89/lib/bottletlsdaemon.py
upd89/lib/configloader.py
upd89/lib/httpsclientauthconnection.py
upd89/lib/log.py
upd89/lib/mission.py
upd89/lib/persist.py
upd89/lib/pkg.py
upd89/lib/sysinfo.py
upd89/lib/upstream.py